nonebot_plugin_bawiki-0.11.3.dist-info/METADATA
nonebot_plugin_bawiki-0.11.3.dist-info/WHEEL
nonebot_plugin_bawiki-0.11.3.dist-info/licenses/LICENSE
nonebot_plugin_bawiki/__init__.py
nonebot_plugin_bawiki/command/__init__.py
nonebot_plugin_bawiki/command/arona.py
nonebot_plugin_bawiki/command/calender.py
nonebot_plugin_bawiki/command/clear_cache.py
nonebot_plugin_bawiki/command/craft.py
nonebot_plugin_bawiki/command/emoji.py
nonebot_plugin_bawiki/command/event.py
nonebot_plugin_bawiki/command/furniture.py
nonebot_plugin_bawiki/command/gacha.py
nonebot_plugin_bawiki/command/level_guide.py
nonebot_plugin_bawiki/command/logo_generate.py
nonebot_plugin_bawiki/command/manga.py
nonebot_plugin_bawiki/command/raid.py
nonebot_plugin_bawiki/command/raid_data_cn.py
nonebot_plugin_bawiki/command/stu_fav.py
nonebot_plugin_bawiki/command/stu_rank.py
nonebot_plugin_bawiki/command/stu_wiki_gamekee.py
nonebot_plugin_bawiki/command/stu_wiki_schale.py
nonebot_plugin_bawiki/command/time_atk.py
nonebot_plugin_bawiki/command/update_future.py
nonebot_plugin_bawiki/command/voice.py
nonebot_plugin_bawiki/compat.py
nonebot_plugin_bawiki/config.py
nonebot_plugin_bawiki/data/__init__.py
nonebot_plugin_bawiki/data/arona.py
nonebot_plugin_bawiki/data/bawiki.py
nonebot_plugin_bawiki/data/gacha.py
nonebot_plugin_bawiki/data/gamekee.py
nonebot_plugin_bawiki/data/logo_generate.py
nonebot_plugin_bawiki/data/playwright.py
nonebot_plugin_bawiki/data/schaledb.py
nonebot_plugin_bawiki/data/shittim_chest.py
nonebot_plugin_bawiki/help/__init__.py
nonebot_plugin_bawiki/help/const.py
nonebot_plugin_bawiki/help/manual.py
nonebot_plugin_bawiki/help/pic_menu.py
nonebot_plugin_bawiki/resource/__init__.py
nonebot_plugin_bawiki/resource/res/gacha/gacha_bg.webp
nonebot_plugin_bawiki/resource/res/gacha/gacha_bg_old.webp
nonebot_plugin_bawiki/resource/res/gacha/gacha_card_bg.png
nonebot_plugin_bawiki/resource/res/gacha/gacha_card_mask.png
nonebot_plugin_bawiki/resource/res/gacha/gacha_new.png
nonebot_plugin_bawiki/resource/res/gacha/gacha_pickup.png
nonebot_plugin_bawiki/resource/res/gacha/gacha_star.png
nonebot_plugin_bawiki/resource/res/gacha/gacha_stu_err.png
nonebot_plugin_bawiki-0.11.3.dist-info/RECORD
