Metadata-Version: 2.1
Name: nonebot-plugin-bawiki
Version: 0.11.3
Summary: A nonebot2 plugin for Blue Archive.
Keywords: blue archive,nonebot,nonebot2,bot,qq
Home-page: https://github.com/lgc2333/nonebot-plugin-bawiki/
Author-Email: student_2333 <lgc2333@126.com>
License: MIT
Classifier: Natural Language :: Chinese (Simplified)
Classifier: Topic :: Communications
Classifier: Topic :: Communications :: Chat
Classifier: Topic :: Communications :: Chat :: ICQ
Classifier: Topic :: Games/Entertainment
Classifier: Topic :: Games/Entertainment :: Board Games
Classifier: Topic :: Games/Entertainment :: Turn Based Strategy
Classifier: Topic :: Games/Entertainment :: Side-Scrolling/Arcade Games
Classifier: Topic :: Internet
Classifier: Topic :: Internet :: WWW/HTTP
Classifier: Topic :: Internet :: WWW/HTTP :: Dynamic Content
Classifier: Topic :: Internet :: WWW/HTTP :: Dynamic Content :: Wiki
Project-URL: Homepage, https://github.com/lgc2333/nonebot-plugin-bawiki/
Requires-Python: <4.0,>=3.9
Requires-Dist: nonebot2>=2.2.0
Requires-Dist: nonebot-adapter-onebot>=2.3.1
Requires-Dist: nonebot-plugin-htmlrender>=0.2.2
Requires-Dist: nonebot-plugin-apscheduler>=0.3.0
Requires-Dist: beautifulsoup4>=4.11.1
Requires-Dist: lxml>=4.9.1
Requires-Dist: pil-utils>=0.1.4
Requires-Dist: httpx>=0.24
Requires-Dist: pypinyin>=0.49.0
Requires-Dist: yarl>=1.9.2
Requires-Dist: async-lru>=2.0.4
Requires-Dist: matplotlib>=3.7.4
Requires-Dist: pytz>=2023.3.post1
Requires-Dist: nonebot-plugin-PicMenu>=0.2; extra == "menu"
Provides-Extra: menu
